Metadata-Version: 1.1
Name: batchfilerename
Version: 1.0
Summary: Batch file renaming utility
Home-page: https://github.com/dmnfarrell/batchfilerename
Author: Damien Farrell
Author-email: farrell.damien@gmail.com
License: GPL v3
Keywords: tkinter,file management,tools
Platform: UNKNOWN
Classifier: Operating System :: OS Independent
Classifier: Programming Language :: Python :: 3
Classifier: Operating System :: MacOS :: MacOS X
Classifier: Operating System :: Microsoft :: Windows
Classifier: Operating System :: POSIX
Classifier: Topic :: Utilities
Classifier: License :: OSI Approved :: GNU General Public License v3 (GPLv3)
Classifier: Development Status :: 4 - Beta
